<TextureAtlas imagePath="sprites.png">
	<SubTexture name="0.png" x="0" y="1444" width="203" height="294"/>
	<SubTexture name="1.png" x="0" y="578" width="210" height="287"/>
	<SubTexture name="2.png" x="0" y="0" width="220" height="287"/>
	<SubTexture name="3.png" x="0" y="289" width="215" height="287"/>
	<SubTexture name="4.png" x="0" y="867" width="207" height="287"/>
	<SubTexture name="5.png" x="0" y="1156" width="205" height="286"/>
	<SubTexture name="6.png" x="0" y="289" width="215" height="287"/>
	<SubTexture name="7.png" x="0" y="0" width="220" height="287"/>
	<SubTexture name="8.png" x="0" y="578" width="210" height="287"/>
	<SubTexture name="9.png" x="0" y="1444" width="203" height="294"/>
</TextureAtlas>